book_writer/__init__.py
book_writer/book_writer.py
long_ebook_generator_ai-1.0.5.dist-info/METADATA
long_ebook_generator_ai-1.0.5.dist-info/WHEEL
long_ebook_generator_ai-1.0.5.dist-info/top_level.txt
long_ebook_generator_ai-1.0.5.dist-info/RECORD
