Metadata-Version: 2.1
Name: long-ebook-generator-ai
Version: 1.0.5
Summary: An A.I. tool for generating long Kindle ebooks based on a prompt
Home-page: UNKNOWN
Author: Alexis Kirke
Author-email: alexiskirke2@gmail.com
License: UNKNOWN
Platform: UNKNOWN
Classifier: Development Status :: 3 - Alpha
Classifier: Intended Audience :: Developers
Classifier: License :: OSI Approved :: MIT License
Classifier: Operating System :: OS Independent
Classifier: Programming Language :: Python :: 3
Classifier: Programming Language :: Python :: 3.7
Classifier: Programming Language :: Python :: 3.8
Classifier: Programming Language :: Python :: 3.9
Classifier: Programming Language :: Python :: 3.10
Requires-Python: >=3.7
Requires-Dist: openai
Requires-Dist: tiktoken
Requires-Dist: ebooklib
Requires-Dist: Pillow
Requires-Dist: requests
Requires-Dist: latex2mathml
